{
  "name": "SRL_DC_IPV6",
  "type": "clab",
  "clab": {
    "config": {
      "prefix": "",
      "mgmt": {
        "network": "clab",
        "bridge": "br-929d87bbfd2e",
        "ipv4-subnet": "172.20.20.0/24",
        "ipv4-gw": "172.20.20.1",
        "ipv6-subnet": "3fff:172:20:20::/64",
        "ipv6-gw": "3fff:172:20:20::1",
        "external-access": true
      }
    }
  },
  "ssh-pub-keys": ["ssh-ed25519 AAAAC3NzaC1lZDI1NTE5AAAAIKB7qkZv2ArHb8yROjbyR6vl+xX0HvP5+563mQ7Ism+5"],
  "nodes": {
    "h1-100": {
      "index": "0",
      "shortname": "h1-100",
      "longname": "h1-100",
      "fqdn": "h1-100.SRL_DC_IPV6.io",
      "group": "",
      "labdir": "/home/ashakra/srl-ipv6/clab-SRL_DC_IPV6/h1-100",
      "kind": "linux",
      "image": "ghcr.io/hellt/network-multitool",
      "mgmt-net": "",
      "mgmt-intf": "",
      "mgmt-ipv4-address": "172.20.20.8",
      "mgmt-ipv4-prefix-length": 24,
      "mgmt-ipv6-address": "3fff:172:20:20::8",
      "mgmt-ipv6-prefix-length": 64,
      "mac-address": "",
      "labels": {
        "clab-git-branch": "main",
        "clab-git-hash": "fae6a04",
        "clab-mgmt-net-bridge": "br-929d87bbfd2e",
        "clab-node-group": "",
        "clab-node-kind": "linux",
        "clab-node-lab-dir": "/home/ashakra/srl-ipv6/clab-SRL_DC_IPV6/h1-100",
        "clab-node-longname": "h1-100",
        "clab-node-name": "h1-100",
        "clab-node-type": "linux",
        "clab-owner": "ashakra",
        "clab-topo-file": "/home/ashakra/srl-ipv6/srl_ipv6.yaml",
        "containerlab": "SRL_DC_IPV6"
      },
      "port-bindings": [
        {
          "host-ip": "",
          "host-port": 0,
          "port": 443,
          "protocol": "tcp"
        },
        {
          "host-ip": "",
          "host-port": 0,
          "port": 80,
          "protocol": "tcp"
        }
      ]
    },
    "h1-101": {
      "index": "1",
      "shortname": "h1-101",
      "longname": "h1-101",
      "fqdn": "h1-101.SRL_DC_IPV6.io",
      "group": "",
      "labdir": "/home/ashakra/srl-ipv6/clab-SRL_DC_IPV6/h1-101",
      "kind": "linux",
      "image": "ghcr.io/hellt/network-multitool",
      "mgmt-net": "",
      "mgmt-intf": "",
      "mgmt-ipv4-address": "172.20.20.6",
      "mgmt-ipv4-prefix-length": 24,
      "mgmt-ipv6-address": "3fff:172:20:20::6",
      "mgmt-ipv6-prefix-length": 64,
      "mac-address": "",
      "labels": {
        "clab-git-branch": "main",
        "clab-git-hash": "fae6a04",
        "clab-mgmt-net-bridge": "br-929d87bbfd2e",
        "clab-node-group": "",
        "clab-node-kind": "linux",
        "clab-node-lab-dir": "/home/ashakra/srl-ipv6/clab-SRL_DC_IPV6/h1-101",
        "clab-node-longname": "h1-101",
        "clab-node-name": "h1-101",
        "clab-node-type": "linux",
        "clab-owner": "ashakra",
        "clab-topo-file": "/home/ashakra/srl-ipv6/srl_ipv6.yaml",
        "containerlab": "SRL_DC_IPV6"
      },
      "port-bindings": [
        {
          "host-ip": "",
          "host-port": 0,
          "port": 443,
          "protocol": "tcp"
        },
        {
          "host-ip": "",
          "host-port": 0,
          "port": 80,
          "protocol": "tcp"
        }
      ]
    },
    "h102": {
      "index": "2",
      "shortname": "h102",
      "longname": "h102",
      "fqdn": "h102.SRL_DC_IPV6.io",
      "group": "",
      "labdir": "/home/ashakra/srl-ipv6/clab-SRL_DC_IPV6/h102",
      "kind": "linux",
      "image": "ghcr.io/hellt/network-multitool",
      "mgmt-net": "",
      "mgmt-intf": "",
      "mgmt-ipv4-address": "172.20.20.3",
      "mgmt-ipv4-prefix-length": 24,
      "mgmt-ipv6-address": "3fff:172:20:20::3",
      "mgmt-ipv6-prefix-length": 64,
      "mac-address": "",
      "labels": {
        "clab-git-branch": "main",
        "clab-git-hash": "fae6a04",
        "clab-mgmt-net-bridge": "br-929d87bbfd2e",
        "clab-node-group": "",
        "clab-node-kind": "linux",
        "clab-node-lab-dir": "/home/ashakra/srl-ipv6/clab-SRL_DC_IPV6/h102",
        "clab-node-longname": "h102",
        "clab-node-name": "h102",
        "clab-node-type": "linux",
        "clab-owner": "ashakra",
        "clab-topo-file": "/home/ashakra/srl-ipv6/srl_ipv6.yaml",
        "containerlab": "SRL_DC_IPV6"
      },
      "port-bindings": [
        {
          "host-ip": "",
          "host-port": 0,
          "port": 443,
          "protocol": "tcp"
        },
        {
          "host-ip": "",
          "host-port": 0,
          "port": 80,
          "protocol": "tcp"
        }
      ]
    },
    "h12": {
      "index": "3",
      "shortname": "h12",
      "longname": "h12",
      "fqdn": "h12.SRL_DC_IPV6.io",
      "group": "",
      "labdir": "/home/ashakra/srl-ipv6/clab-SRL_DC_IPV6/h12",
      "kind": "linux",
      "image": "ghcr.io/hellt/network-multitool",
      "mgmt-net": "",
      "mgmt-intf": "",
      "mgmt-ipv4-address": "172.20.20.9",
      "mgmt-ipv4-prefix-length": 24,
      "mgmt-ipv6-address": "3fff:172:20:20::9",
      "mgmt-ipv6-prefix-length": 64,
      "mac-address": "",
      "labels": {
        "clab-git-branch": "main",
        "clab-git-hash": "fae6a04",
        "clab-mgmt-net-bridge": "br-929d87bbfd2e",
        "clab-node-group": "",
        "clab-node-kind": "linux",
        "clab-node-lab-dir": "/home/ashakra/srl-ipv6/clab-SRL_DC_IPV6/h12",
        "clab-node-longname": "h12",
        "clab-node-name": "h12",
        "clab-node-type": "linux",
        "clab-owner": "ashakra",
        "clab-topo-file": "/home/ashakra/srl-ipv6/srl_ipv6.yaml",
        "containerlab": "SRL_DC_IPV6"
      },
      "port-bindings": [
        {
          "host-ip": "",
          "host-port": 0,
          "port": 443,
          "protocol": "tcp"
        },
        {
          "host-ip": "",
          "host-port": 0,
          "port": 80,
          "protocol": "tcp"
        }
      ]
    },
    "h2": {
      "index": "4",
      "shortname": "h2",
      "longname": "h2",
      "fqdn": "h2.SRL_DC_IPV6.io",
      "group": "",
      "labdir": "/home/ashakra/srl-ipv6/clab-SRL_DC_IPV6/h2",
      "kind": "linux",
      "image": "ghcr.io/hellt/network-multitool",
      "mgmt-net": "",
      "mgmt-intf": "",
      "mgmt-ipv4-address": "172.20.20.2",
      "mgmt-ipv4-prefix-length": 24,
      "mgmt-ipv6-address": "3fff:172:20:20::2",
      "mgmt-ipv6-prefix-length": 64,
      "mac-address": "",
      "labels": {
        "clab-git-branch": "main",
        "clab-git-hash": "fae6a04",
        "clab-mgmt-net-bridge": "br-929d87bbfd2e",
        "clab-node-group": "",
        "clab-node-kind": "linux",
        "clab-node-lab-dir": "/home/ashakra/srl-ipv6/clab-SRL_DC_IPV6/h2",
        "clab-node-longname": "h2",
        "clab-node-name": "h2",
        "clab-node-type": "linux",
        "clab-owner": "ashakra",
        "clab-topo-file": "/home/ashakra/srl-ipv6/srl_ipv6.yaml",
        "containerlab": "SRL_DC_IPV6"
      },
      "port-bindings": [
        {
          "host-ip": "",
          "host-port": 0,
          "port": 443,
          "protocol": "tcp"
        },
        {
          "host-ip": "",
          "host-port": 0,
          "port": 80,
          "protocol": "tcp"
        }
      ]
    },
    "h202": {
      "index": "5",
      "shortname": "h202",
      "longname": "h202",
      "fqdn": "h202.SRL_DC_IPV6.io",
      "group": "",
      "labdir": "/home/ashakra/srl-ipv6/clab-SRL_DC_IPV6/h202",
      "kind": "linux",
      "image": "ghcr.io/hellt/network-multitool",
      "mgmt-net": "",
      "mgmt-intf": "",
      "mgmt-ipv4-address": "172.20.20.14",
      "mgmt-ipv4-prefix-length": 24,
      "mgmt-ipv6-address": "3fff:172:20:20::e",
      "mgmt-ipv6-prefix-length": 64,
      "mac-address": "",
      "labels": {
        "clab-git-branch": "main",
        "clab-git-hash": "fae6a04",
        "clab-mgmt-net-bridge": "br-929d87bbfd2e",
        "clab-node-group": "",
        "clab-node-kind": "linux",
        "clab-node-lab-dir": "/home/ashakra/srl-ipv6/clab-SRL_DC_IPV6/h202",
        "clab-node-longname": "h202",
        "clab-node-name": "h202",
        "clab-node-type": "linux",
        "clab-owner": "ashakra",
        "clab-topo-file": "/home/ashakra/srl-ipv6/srl_ipv6.yaml",
        "containerlab": "SRL_DC_IPV6"
      },
      "port-bindings": [
        {
          "host-ip": "",
          "host-port": 0,
          "port": 443,
          "protocol": "tcp"
        },
        {
          "host-ip": "",
          "host-port": 0,
          "port": 80,
          "protocol": "tcp"
        }
      ]
    },
    "h302": {
      "index": "6",
      "shortname": "h302",
      "longname": "h302",
      "fqdn": "h302.SRL_DC_IPV6.io",
      "group": "",
      "labdir": "/home/ashakra/srl-ipv6/clab-SRL_DC_IPV6/h302",
      "kind": "linux",
      "image": "ghcr.io/hellt/network-multitool",
      "mgmt-net": "",
      "mgmt-intf": "",
      "mgmt-ipv4-address": "172.20.20.10",
      "mgmt-ipv4-prefix-length": 24,
      "mgmt-ipv6-address": "3fff:172:20:20::a",
      "mgmt-ipv6-prefix-length": 64,
      "mac-address": "",
      "labels": {
        "clab-git-branch": "main",
        "clab-git-hash": "fae6a04",
        "clab-mgmt-net-bridge": "br-929d87bbfd2e",
        "clab-node-group": "",
        "clab-node-kind": "linux",
        "clab-node-lab-dir": "/home/ashakra/srl-ipv6/clab-SRL_DC_IPV6/h302",
        "clab-node-longname": "h302",
        "clab-node-name": "h302",
        "clab-node-type": "linux",
        "clab-owner": "ashakra",
        "clab-topo-file": "/home/ashakra/srl-ipv6/srl_ipv6.yaml",
        "containerlab": "SRL_DC_IPV6"
      },
      "port-bindings": [
        {
          "host-ip": "",
          "host-port": 0,
          "port": 80,
          "protocol": "tcp"
        },
        {
          "host-ip": "",
          "host-port": 0,
          "port": 443,
          "protocol": "tcp"
        }
      ]
    },
    "h402": {
      "index": "7",
      "shortname": "h402",
      "longname": "h402",
      "fqdn": "h402.SRL_DC_IPV6.io",
      "group": "",
      "labdir": "/home/ashakra/srl-ipv6/clab-SRL_DC_IPV6/h402",
      "kind": "linux",
      "image": "ghcr.io/hellt/network-multitool",
      "mgmt-net": "",
      "mgmt-intf": "",
      "mgmt-ipv4-address": "172.20.20.7",
      "mgmt-ipv4-prefix-length": 24,
      "mgmt-ipv6-address": "3fff:172:20:20::7",
      "mgmt-ipv6-prefix-length": 64,
      "mac-address": "",
      "labels": {
        "clab-git-branch": "main",
        "clab-git-hash": "fae6a04",
        "clab-mgmt-net-bridge": "br-929d87bbfd2e",
        "clab-node-group": "",
        "clab-node-kind": "linux",
        "clab-node-lab-dir": "/home/ashakra/srl-ipv6/clab-SRL_DC_IPV6/h402",
        "clab-node-longname": "h402",
        "clab-node-name": "h402",
        "clab-node-type": "linux",
        "clab-owner": "ashakra",
        "clab-topo-file": "/home/ashakra/srl-ipv6/srl_ipv6.yaml",
        "containerlab": "SRL_DC_IPV6"
      },
      "port-bindings": [
        {
          "host-ip": "",
          "host-port": 0,
          "port": 443,
          "protocol": "tcp"
        },
        {
          "host-ip": "",
          "host-port": 0,
          "port": 80,
          "protocol": "tcp"
        }
      ]
    },
    "l1": {
      "index": "8",
      "shortname": "l1",
      "longname": "l1",
      "fqdn": "l1.SRL_DC_IPV6.io",
      "group": "",
      "labdir": "/home/ashakra/srl-ipv6/clab-SRL_DC_IPV6/l1",
      "kind": "srl",
      "image": "ghcr.io/nokia/srlinux:25.7.2",
      "mgmt-net": "",
      "mgmt-intf": "",
      "mgmt-ipv4-address": "172.20.20.5",
      "mgmt-ipv4-prefix-length": 24,
      "mgmt-ipv6-address": "3fff:172:20:20::5",
      "mgmt-ipv6-prefix-length": 64,
      "mac-address": "1a:b6:08:00:00:00",
      "labels": {
        "clab-git-branch": "main",
        "clab-git-hash": "fae6a04",
        "clab-mgmt-net-bridge": "br-929d87bbfd2e",
        "clab-node-group": "",
        "clab-node-kind": "srl",
        "clab-node-lab-dir": "/home/ashakra/srl-ipv6/clab-SRL_DC_IPV6/l1",
        "clab-node-longname": "l1",
        "clab-node-name": "l1",
        "clab-node-type": "ixr-d3l",
        "clab-owner": "ashakra",
        "clab-topo-file": "/home/ashakra/srl-ipv6/srl_ipv6.yaml",
        "containerlab": "SRL_DC_IPV6"
      },
      "port-bindings": [
      ]
    },
    "l2": {
      "index": "9",
      "shortname": "l2",
      "longname": "l2",
      "fqdn": "l2.SRL_DC_IPV6.io",
      "group": "",
      "labdir": "/home/ashakra/srl-ipv6/clab-SRL_DC_IPV6/l2",
      "kind": "srl",
      "image": "ghcr.io/nokia/srlinux:25.7.2",
      "mgmt-net": "",
      "mgmt-intf": "",
      "mgmt-ipv4-address": "172.20.20.4",
      "mgmt-ipv4-prefix-length": 24,
      "mgmt-ipv6-address": "3fff:172:20:20::4",
      "mgmt-ipv6-prefix-length": 64,
      "mac-address": "1a:8d:09:00:00:00",
      "labels": {
        "clab-git-branch": "main",
        "clab-git-hash": "fae6a04",
        "clab-mgmt-net-bridge": "br-929d87bbfd2e",
        "clab-node-group": "",
        "clab-node-kind": "srl",
        "clab-node-lab-dir": "/home/ashakra/srl-ipv6/clab-SRL_DC_IPV6/l2",
        "clab-node-longname": "l2",
        "clab-node-name": "l2",
        "clab-node-type": "ixr-d3l",
        "clab-owner": "ashakra",
        "clab-topo-file": "/home/ashakra/srl-ipv6/srl_ipv6.yaml",
        "containerlab": "SRL_DC_IPV6"
      },
      "port-bindings": [
      ]
    },
    "l3": {
      "index": "10",
      "shortname": "l3",
      "longname": "l3",
      "fqdn": "l3.SRL_DC_IPV6.io",
      "group": "",
      "labdir": "/home/ashakra/srl-ipv6/clab-SRL_DC_IPV6/l3",
      "kind": "srl",
      "image": "ghcr.io/nokia/srlinux:25.7.2",
      "mgmt-net": "",
      "mgmt-intf": "",
      "mgmt-ipv4-address": "172.20.20.12",
      "mgmt-ipv4-prefix-length": 24,
      "mgmt-ipv6-address": "3fff:172:20:20::c",
      "mgmt-ipv6-prefix-length": 64,
      "mac-address": "1a:f1:0a:00:00:00",
      "labels": {
        "clab-git-branch": "main",
        "clab-git-hash": "fae6a04",
        "clab-mgmt-net-bridge": "br-929d87bbfd2e",
        "clab-node-group": "",
        "clab-node-kind": "srl",
        "clab-node-lab-dir": "/home/ashakra/srl-ipv6/clab-SRL_DC_IPV6/l3",
        "clab-node-longname": "l3",
        "clab-node-name": "l3",
        "clab-node-type": "ixr-d3l",
        "clab-owner": "ashakra",
        "clab-topo-file": "/home/ashakra/srl-ipv6/srl_ipv6.yaml",
        "containerlab": "SRL_DC_IPV6"
      },
      "port-bindings": [
      ]
    },
    "l4": {
      "index": "11",
      "shortname": "l4",
      "longname": "l4",
      "fqdn": "l4.SRL_DC_IPV6.io",
      "group": "",
      "labdir": "/home/ashakra/srl-ipv6/clab-SRL_DC_IPV6/l4",
      "kind": "srl",
      "image": "ghcr.io/nokia/srlinux:25.7.2",
      "mgmt-net": "",
      "mgmt-intf": "",
      "mgmt-ipv4-address": "172.20.20.13",
      "mgmt-ipv4-prefix-length": 24,
      "mgmt-ipv6-address": "3fff:172:20:20::d",
      "mgmt-ipv6-prefix-length": 64,
      "mac-address": "1a:ca:0b:00:00:00",
      "labels": {
        "clab-git-branch": "main",
        "clab-git-hash": "fae6a04",
        "clab-mgmt-net-bridge": "br-929d87bbfd2e",
        "clab-node-group": "",
        "clab-node-kind": "srl",
        "clab-node-lab-dir": "/home/ashakra/srl-ipv6/clab-SRL_DC_IPV6/l4",
        "clab-node-longname": "l4",
        "clab-node-name": "l4",
        "clab-node-type": "ixr-d3l",
        "clab-owner": "ashakra",
        "clab-topo-file": "/home/ashakra/srl-ipv6/srl_ipv6.yaml",
        "containerlab": "SRL_DC_IPV6"
      },
      "port-bindings": [
      ]
    },
    "s1": {
      "index": "12",
      "shortname": "s1",
      "longname": "s1",
      "fqdn": "s1.SRL_DC_IPV6.io",
      "group": "",
      "labdir": "/home/ashakra/srl-ipv6/clab-SRL_DC_IPV6/s1",
      "kind": "srl",
      "image": "ghcr.io/nokia/srlinux:25.7.2",
      "mgmt-net": "",
      "mgmt-intf": "",
      "mgmt-ipv4-address": "172.20.20.11",
      "mgmt-ipv4-prefix-length": 24,
      "mgmt-ipv6-address": "3fff:172:20:20::b",
      "mgmt-ipv6-prefix-length": 64,
      "mac-address": "1a:83:0c:00:00:00",
      "labels": {
        "clab-git-branch": "main",
        "clab-git-hash": "fae6a04",
        "clab-mgmt-net-bridge": "br-929d87bbfd2e",
        "clab-node-group": "",
        "clab-node-kind": "srl",
        "clab-node-lab-dir": "/home/ashakra/srl-ipv6/clab-SRL_DC_IPV6/s1",
        "clab-node-longname": "s1",
        "clab-node-name": "s1",
        "clab-node-type": "ixr-d3l",
        "clab-owner": "ashakra",
        "clab-topo-file": "/home/ashakra/srl-ipv6/srl_ipv6.yaml",
        "containerlab": "SRL_DC_IPV6"
      },
      "port-bindings": [
      ]
    },
    "s2": {
      "index": "13",
      "shortname": "s2",
      "longname": "s2",
      "fqdn": "s2.SRL_DC_IPV6.io",
      "group": "",
      "labdir": "/home/ashakra/srl-ipv6/clab-SRL_DC_IPV6/s2",
      "kind": "srl",
      "image": "ghcr.io/nokia/srlinux:25.7.2",
      "mgmt-net": "",
      "mgmt-intf": "",
      "mgmt-ipv4-address": "172.20.20.15",
      "mgmt-ipv4-prefix-length": 24,
      "mgmt-ipv6-address": "3fff:172:20:20::f",
      "mgmt-ipv6-prefix-length": 64,
      "mac-address": "1a:61:0d:00:00:00",
      "labels": {
        "clab-git-branch": "main",
        "clab-git-hash": "fae6a04",
        "clab-mgmt-net-bridge": "br-929d87bbfd2e",
        "clab-node-group": "",
        "clab-node-kind": "srl",
        "clab-node-lab-dir": "/home/ashakra/srl-ipv6/clab-SRL_DC_IPV6/s2",
        "clab-node-longname": "s2",
        "clab-node-name": "s2",
        "clab-node-type": "ixr-d3l",
        "clab-owner": "ashakra",
        "clab-topo-file": "/home/ashakra/srl-ipv6/srl_ipv6.yaml",
        "containerlab": "SRL_DC_IPV6"
      },
      "port-bindings": [
      ]
    }
  },
  "links": [
    {
      "endpoints": {
        "a": {
          "node": "s1",
          "interface": "e1-1",
          "mac": "aa:c1:ab:f0:ca:fa",
          "peer": "z"
        },
        "z": {
          "node": "l1",
          "interface": "e1-1",
          "mac": "aa:c1:ab:24:5a:58",
          "peer": "a"
        }
      }
    },
    {
      "endpoints": {
        "a": {
          "node": "s1",
          "interface": "e1-2",
          "mac": "aa:c1:ab:4d:a7:a2",
          "peer": "z"
        },
        "z": {
          "node": "l2",
          "interface": "e1-1",
          "mac": "aa:c1:ab:5c:bb:75",
          "peer": "a"
        }
      }
    },
    {
      "endpoints": {
        "a": {
          "node": "s2",
          "interface": "e1-1",
          "mac": "aa:c1:ab:5f:b8:73",
          "peer": "z"
        },
        "z": {
          "node": "l1",
          "interface": "e1-2",
          "mac": "aa:c1:ab:c7:9a:5c",
          "peer": "a"
        }
      }
    },
    {
      "endpoints": {
        "a": {
          "node": "s2",
          "interface": "e1-2",
          "mac": "aa:c1:ab:e7:c6:5b",
          "peer": "z"
        },
        "z": {
          "node": "l2",
          "interface": "e1-2",
          "mac": "aa:c1:ab:97:05:85",
          "peer": "a"
        }
      }
    },
    {
      "endpoints": {
        "a": {
          "node": "s1",
          "interface": "e1-3",
          "mac": "aa:c1:ab:69:81:c8",
          "peer": "z"
        },
        "z": {
          "node": "l3",
          "interface": "e1-1",
          "mac": "aa:c1:ab:21:ca:bc",
          "peer": "a"
        }
      }
    },
    {
      "endpoints": {
        "a": {
          "node": "s2",
          "interface": "e1-3",
          "mac": "aa:c1:ab:03:56:1d",
          "peer": "z"
        },
        "z": {
          "node": "l3",
          "interface": "e1-2",
          "mac": "aa:c1:ab:87:1d:81",
          "peer": "a"
        }
      }
    },
    {
      "endpoints": {
        "a": {
          "node": "s1",
          "interface": "e1-4",
          "mac": "aa:c1:ab:2d:a3:89",
          "peer": "z"
        },
        "z": {
          "node": "l4",
          "interface": "e1-1",
          "mac": "aa:c1:ab:9f:65:5d",
          "peer": "a"
        }
      }
    },
    {
      "endpoints": {
        "a": {
          "node": "s2",
          "interface": "e1-4",
          "mac": "aa:c1:ab:ef:7e:5e",
          "peer": "z"
        },
        "z": {
          "node": "l4",
          "interface": "e1-2",
          "mac": "aa:c1:ab:82:3f:9f",
          "peer": "a"
        }
      }
    },
    {
      "endpoints": {
        "a": {
          "node": "l1",
          "interface": "e1-5",
          "mac": "aa:c1:ab:32:30:1b",
          "peer": "z"
        },
        "z": {
          "node": "h1-100",
          "interface": "eth1",
          "mac": "aa:c1:ab:fd:c5:3b",
          "peer": "a"
        }
      }
    },
    {
      "endpoints": {
        "a": {
          "node": "l2",
          "interface": "e1-5",
          "mac": "aa:c1:ab:23:94:76",
          "peer": "z"
        },
        "z": {
          "node": "h1-101",
          "interface": "eth1",
          "mac": "aa:c1:ab:cd:87:92",
          "peer": "a"
        }
      }
    },
    {
      "endpoints": {
        "a": {
          "node": "l1",
          "interface": "e1-10",
          "mac": "aa:c1:ab:49:51:93",
          "peer": "z"
        },
        "z": {
          "node": "h12",
          "interface": "eth1",
          "mac": "aa:c1:ab:8c:e9:a1",
          "peer": "a"
        }
      }
    },
    {
      "endpoints": {
        "a": {
          "node": "l2",
          "interface": "e1-10",
          "mac": "aa:c1:ab:bf:b9:5e",
          "peer": "z"
        },
        "z": {
          "node": "h12",
          "interface": "eth2",
          "mac": "aa:c1:ab:0a:dc:9e",
          "peer": "a"
        }
      }
    },
    {
      "endpoints": {
        "a": {
          "node": "l3",
          "interface": "e1-10",
          "mac": "aa:c1:ab:5d:5b:af",
          "peer": "z"
        },
        "z": {
          "node": "h2",
          "interface": "eth1",
          "mac": "aa:c1:ab:d8:36:ba",
          "peer": "a"
        }
      }
    },
    {
      "endpoints": {
        "a": {
          "node": "l1",
          "interface": "e1-11",
          "mac": "aa:c1:ab:16:ff:97",
          "peer": "z"
        },
        "z": {
          "node": "h102",
          "interface": "eth1",
          "mac": "aa:c1:ab:25:2f:24",
          "peer": "a"
        }
      }
    },
    {
      "endpoints": {
        "a": {
          "node": "l2",
          "interface": "e1-11",
          "mac": "aa:c1:ab:da:3e:55",
          "peer": "z"
        },
        "z": {
          "node": "h202",
          "interface": "eth1",
          "mac": "aa:c1:ab:67:63:b3",
          "peer": "a"
        }
      }
    },
    {
      "endpoints": {
        "a": {
          "node": "l3",
          "interface": "e1-11",
          "mac": "aa:c1:ab:19:49:e0",
          "peer": "z"
        },
        "z": {
          "node": "h302",
          "interface": "eth1",
          "mac": "aa:c1:ab:d0:c0:06",
          "peer": "a"
        }
      }
    },
    {
      "endpoints": {
        "a": {
          "node": "l4",
          "interface": "e1-11",
          "mac": "aa:c1:ab:55:10:f6",
          "peer": "z"
        },
        "z": {
          "node": "h402",
          "interface": "eth1",
          "mac": "aa:c1:ab:96:dc:d2",
          "peer": "a"
        }
      }
    }
  ]
}
